feynman/__init__.py
feynman/colors.py
feynman/constants.py
feynman/vectors.py
feynman/core/__init__.py
feynman/core/drawable.py
feynman/core/lines.py
feynman/core/operators.py
feynman/core/util.py
feynman/core/vertex.py
feynman/diagrams/__init__.py
feynman/diagrams/diagrams.py
feynman/diagrams/plotter.py
feynman/tests/__init__.py
feynman/tests/test_v2_1_simple.py
feynman/tests/test_v2_21_dyson.py
feynman/tests/test_v2_22_SigmaHedin.py
feynman/tests/test_v2_2_wiggly.py
feynman/tests/test_v2_3_loopy.py
feynman/tests/test_v2_4_circle.py
feynman/tests/test_v2_5_double.py
feynman/tests/test_v2_6_polygon.py
feynman/tests/test_v2_7_ellipse.py
feynman/tests/test_v2_8_text.py
feynman/tests/baseline_images/test_v2_1_simple/simple.png
feynman/tests/baseline_images/test_v2_21_dyson/simple.png
feynman/tests/baseline_images/test_v2_22_SigmaHedin/sigma.png
feynman/tests/baseline_images/test_v2_2_wiggly/wiggly.png
feynman/tests/baseline_images/test_v2_3_loopy/loopy.png
feynman/tests/baseline_images/test_v2_4_circle/angle.png
feynman/tests/baseline_images/test_v2_4_circle/simple.png
feynman/tests/baseline_images/test_v2_4_circle/wiggly.png
feynman/tests/baseline_images/test_v2_5_double/double.png
feynman/tests/baseline_images/test_v2_6_polygon/polygon.png
feynman/tests/baseline_images/test_v2_7_ellipse/ellipse.png
feynman/tests/baseline_images/test_v2_8_text/text.png
feynman-2.1.0.dist-info/LICENSE
feynman-2.1.0.dist-info/METADATA
feynman-2.1.0.dist-info/WHEEL
feynman-2.1.0.dist-info/top_level.txt
feynman-2.1.0.dist-info/RECORD
