Metadata-Version: 2.1
Name: feynman
Version: 2.1.0
Summary: Feynman diagrams with python-matplotlib
Home-page: http://gkantonius.github.io/feynman
Author: Gabriel Antonius
Author-email: Gabriel Antonius <gabriel.antonius@gmail.com>
License: GPL
Project-URL: Homepage, https://github.com/GkAntonius/feynman
Project-URL: Bug Tracker, https://github.com/GkAntonius/feynman/issues
Keywords: Feynman diagrams
Classifier: Programming Language :: Python :: 3
Classifier: License :: OSI Approved :: GNU General Public License (GPL)
Classifier: Operating System :: OS Independent
Requires-Python: >=3.7
License-File: LICENSE
Requires-Dist: matplotlib (>=1.1)
Requires-Dist: numpy (>=1.6)
